<?xml version="1.0" encoding="utf-8"?>
<!DOCTYPE hibernate-mapping PUBLIC "-//Hibernate/Hibernate Mapping DTD 3.0//EN"
"http://hibernate.sourceforge.net/hibernate-mapping-3.0.dtd">
<!-- 
    Mapping file autogenerated by MyEclipse Persistence Tools
-->
<hibernate-mapping>
    <class name="com.zx.core.model.SysPermission" table="sys_permission" >
        <id name="id" type="java.lang.Long">
            <column name="ID" />
            <generator class="native" />
        </id>
        <property name="code" type="java.lang.String">
            <column name="CODE" length="64" not-null="true">
                <comment>代码</comment>
            </column>
        </property>
        <property name="name" type="java.lang.String">
            <column name="NAME" length="64" not-null="true">
                <comment>名称</comment>
            </column>
        </property>
        <property name="image" type="java.lang.String">
            <column name="IMAGE" length="128">
                <comment>图片</comment>
            </column>
        </property>
        <property name="isEnable" type="java.lang.Integer">
            <column name="IS_ENABLE" not-null="true">
                <comment>是否启用</comment>
            </column>
        </property>
        <property name="description" type="java.lang.String">
            <column name="DESCRIPTION" length="512">
                <comment>描述</comment>
            </column>
        </property>
        <property name="createTime" type="java.util.Date">
            <column name="CREATE_TIME" length="19" not-null="true">
                <comment>创建时间</comment>
            </column>
        </property>
        <property name="updateTime" type="java.util.Date">
            <column name="UPDATE_TIME" length="19">
                <comment>更新时间</comment>
            </column>
        </property>
        <property name="recordOrder" type="java.lang.Integer">
            <column name="RECORD_ORDER" not-null="true">
                <comment>排序</comment>
            </column>
        </property>
        <property name="recordStatus" type="java.lang.Integer">
            <column name="RECORD_STATUS" not-null="true">
                <comment>状态</comment>
            </column>
        </property>
        <set name="sysRolePermissions" inverse="true">
            <key>
                <column name="SYS_PERMISSION_ID">
                    <comment>权限流水号</comment>
                </column>
            </key>
            <one-to-many class="com.zx.core.model.SysRolePermission" />
        </set>
        <set name="sysMenuPermissions" inverse="true">
            <key>
                <column name="SYS_PERMISSION_ID">
                    <comment>权限流水号</comment>
                </column>
            </key>
            <one-to-many class="com.zx.core.model.SysMenuPermission" />
        </set>
    </class>
</hibernate-mapping>
